cis_checks_7/__init__.py
cis_checks_7/iam_control_1.py
cis_checks_7/logging_control_2.py
cis_checks_7/monitoring_control_3.py
cis_checks_7/networking_control_4.py
cis_checks_7/security_control_5.py
cis_checks_7/utils.py
cis_checks_7-0.0.8.dist-info/METADATA
cis_checks_7-0.0.8.dist-info/WHEEL
cis_checks_7-0.0.8.dist-info/top_level.txt
cis_checks_7-0.0.8.dist-info/RECORD
